py_expression_eval/__init__.py
py_expression_eval/tests.py
py_expression_eval-0.3.14.dist-info/LICENSE
py_expression_eval-0.3.14.dist-info/METADATA
py_expression_eval-0.3.14.dist-info/WHEEL
py_expression_eval-0.3.14.dist-info/top_level.txt
py_expression_eval-0.3.14.dist-info/RECORD
