Metadata-Version: 2.1
Name: py-expression-eval
Version: 0.3.14
Summary: Python Mathematical Expression Evaluator
Home-page: https://github.com/AxiaCore/py-expression-eval/
Author: cansadadeserfeliz
Author-email: vero4ka.ru@gmail.com
License: MIT
Platform: UNKNOWN
Classifier: Development Status :: 5 - Production/Stable
Classifier: Intended Audience :: Developers
Classifier: Programming Language :: Python
Classifier: Programming Language :: Python :: 2
Classifier: Programming Language :: Python :: 2.7
Classifier: Programming Language :: Python :: 3
Classifier: Programming Language :: Python :: 3.5
Classifier: Programming Language :: Python :: 3.6
Classifier: Programming Language :: Python :: 3.7
Classifier: Programming Language :: Python :: 3.8
Classifier: Programming Language :: Python :: 3.9
